etc/dbus-1/system.d/local.vula.services.conf
etc/systemd/system/vula-discover-alt.service
etc/systemd/system/vula-discover-alt.target
etc/systemd/system/vula-discover.service
etc/systemd/system/vula-discover.target
etc/systemd/system/vula-organize-monolithic.service
etc/systemd/system/vula-organize-monolithic.target
etc/systemd/system/vula-organize.service
etc/systemd/system/vula-publish-alt.service
etc/systemd/system/vula-publish-alt.target
etc/systemd/system/vula-publish.service
etc/systemd/system/vula-publish.target
etc/systemd/system/vula.slice
etc/systemd/system/vula.target
test/__init__.py
test/test_common.py
test/test_crypto.py
test/test_discover.py
test/test_engine.py
test/test_peer.py
test/test_sys_pyroute2.py
test/test_verify.py
test/test_wg.py
usr/lib/sysusers.d/vula.conf
usr/share/applications/vula-tray.desktop
usr/share/applications/vula.desktop
usr/share/dbus-1/system-services/local.vula.discover.service
usr/share/dbus-1/system-services/local.vula.discoveralt.service
usr/share/dbus-1/system-services/local.vula.organize.service
usr/share/dbus-1/system-services/local.vula.publish.service
usr/share/dbus-1/system-services/local.vula.publishalt.service
usr/share/icons/vula_gui_icon.png
usr/share/icons/vula/add_ip_to_peer_entry.png
usr/share/icons/vula/cancel.png
usr/share/icons/vula/clipboard.png
usr/share/icons/vula/delete.png
usr/share/icons/vula/edit.png
usr/share/icons/vula/edit_name_entry.png
usr/share/icons/vula/help.png
usr/share/icons/vula/next.png
usr/share/icons/vula/pin_and_verify.png
usr/share/icons/vula/previous.png
usr/share/icons/vula/rediscover.png
usr/share/icons/vula/release_gateway.png
usr/share/icons/vula/repair.png
usr/share/icons/vula/save.png
usr/share/icons/vula/save_blue.png
usr/share/icons/vula/show_qr.png
usr/share/polkit-1/actions/local.vula.organize.Debug.policy
vula/__init__.py
vula/__main__.py
vula/__version__.py
vula/common.py
vula/configure.py
vula/constants.py
vula/csidh.py
vula/discover.py
vula/discover_alt.py
vula-0.2.2024011000.dist-info/LICENSE
vula-0.2.2024011000.dist-info/METADATA
vula-0.2.2024011000.dist-info/WHEEL
vula-0.2.2024011000.dist-info/top_level.txt
vula-0.2.2024011000.dist-info/RECORD
