Metadata-Version: 2.1
Name: vula
Version: 0.2.2024011000
Summary: Automatic local network encryption
Home-page: https://codeberg.org/vula/vula
Author: Vula Authors
Author-email: git@vula.link
Maintainer: Vula Authors
Maintainer-email: git@vula.link
License: GPLv3
Project-URL: Documentation, https://codeberg.org/vula/vula
Project-URL: Source, https://codeberg.org/vula/vula
Keywords: post-quantum cryptography,cryptography,csidh,ctidh,WireGuard,mDNS,encryption,post-quantum,local-area network,privacy,security
Classifier: Programming Language :: Python :: 3
Classifier: License :: OSI Approved :: GNU General Public License v3 (GPLv3)
Classifier: Operating System :: OS Independent
Requires-Python: >=3.10
License-File: LICENSE
Provides-Extra: audio
Requires-Dist: pyaudio ; extra == 'audio'
Requires-Dist: ggwave ; extra == 'audio'
Provides-Extra: test
Requires-Dist: pytest ; extra == 'test'
